llm_prompt_creator/__init__.py
llm_prompt_creator/prompt.py
llm_prompt_creator-0.5.0.dist-info/METADATA
llm_prompt_creator-0.5.0.dist-info/WHEEL
llm_prompt_creator-0.5.0.dist-info/licenses/LICENSE
llm_prompt_creator-0.5.0.dist-info/RECORD
