Metadata-Version: 2.1
Name: llm_prompt_creator
Version: 0.5.0
Summary: Takes a given directory and parses its contents to create a text vectorstore to be consumed in prompts for various LLM models.
Project-URL: Homepage, https://github.com/break-free/fineract-unit-tests-openai
Project-URL: Issues, https://github.com/break-free/fineract-unit-tests-openai/issues
Author-email: Chris Mills <cmills@breakfreesolutions.com>, Zak Alford <zalford@breakfreesolutions.com>
License-File: LICENSE
Classifier: License :: OSI Approved :: MIT License
Classifier: Operating System :: OS Independent
Classifier: Programming Language :: Python :: 3
Requires-Python: >=3.7
Requires-Dist: bs4
Requires-Dist: chromadb
Requires-Dist: data-chunker
Requires-Dist: langchain
Requires-Dist: openai
Requires-Dist: tiktoken
